getsentinel/__init__.py
getsentinel/gs_config.py
getsentinel/gs_downloader.py
getsentinel/gs_localmanager.py
getsentinel/gs_processor.py
getsentinel/gs_stacker.py
getsentinel-0.1.dist-info/METADATA
getsentinel-0.1.dist-info/RECORD
getsentinel-0.1.dist-info/WHEEL
getsentinel-0.1.dist-info/top_level.txt
