Metadata-Version: 2.1
Name: getsentinel
Version: 0.1
Summary: An ESA Sentinel data pipeline.
Home-page: https://bitbucket.org/wirrell/getsentinel
Author: G. Worrall
Author-email: worrall.george@gmail.com
License: Apache 2.0
Project-URL: Documentation, https://getsentinel.readthedocs.io/
Project-URL: Source, https://www.bitbucket.org/wirrell/getsentinel
Platform: UNKNOWN
Requires-Python: >=3.4
Requires-Dist: requests
Requires-Dist: clint
Requires-Dist: pyshp
Requires-Dist: geojson
Requires-Dist: shapely
Requires-Dist: numpy
Requires-Dist: rasterio
